commons.py
constant.py
get_insta_insights.py
setup.py
insights/__init__.py
insights/hashtags.py
insights/htmlutils.py
insights/timings.py
insights/data/index.html.template
insights/data/style.css
instagram/__init__.py
instagram/instagram_data.py
instagram/restmethods.py
instagram_insights-0.2.7.data/data/README.md
instagram_insights-0.2.7.data/data/requirements-test.txt
instagram_insights-0.2.7.data/data/requirements.txt
instagram_insights-0.2.7.data/data/screenshot.png
instagram_insights-0.2.7.dist-info/LICENSE
instagram_insights-0.2.7.dist-info/METADATA
instagram_insights-0.2.7.dist-info/WHEEL
instagram_insights-0.2.7.dist-info/entry_points.txt
instagram_insights-0.2.7.dist-info/top_level.txt
instagram_insights-0.2.7.dist-info/RECORD
