Metadata-Version: 2.1
Name: instagram-insights
Version: 0.2.7
Summary: Get insights about best times to post, and the best tags based on likes, views and impressions.
Home-page: https://github.com/PardhuMadipalli/instagram-insights
Author: Pardhu Madipalli
Author-email: pardhu.madipalli@gmail.com
License: UNKNOWN
Project-URL: Bug Tracker, https://github.com/PardhuMadipalli/instagram-insights/issues
Platform: UNKNOWN
Classifier: Programming Language :: Python :: 3
Classifier: License :: OSI Approved :: MIT License
Classifier: Operating System :: OS Independent
Requires-Python: >=3.7
Requires-Dist: pandas
Requires-Dist: numpy
Requires-Dist: requests
Requires-Dist: matplotlib
